Metadata-Version: 2.1
Name: torchbench
Version: 0.0.31
Summary: Easily benchmark Machine Learning models on selected tasks and datasets - with PyTorch
Home-page: https://sotabench.com
Author: Atlas ML
Author-email: hello@sotabench.com
Maintainer: Atlas ML
Maintainer-email: hello@sotabench.com
License: Apache-2.0
Platform: Windows
Platform: POSIX
Platform: MacOSX
Classifier: Programming Language :: Python :: 3
Classifier: Programming Language :: Python :: 3.6
Classifier: Programming Language :: Python :: 3.7
Classifier: License :: OSI Approved :: Apache Software License
Classifier: Operating System :: OS Independent
Requires-Dist: albumentations (>=0.3.0)
Requires-Dist: numpy
Requires-Dist: opencv-python (>=4.1.0.25)
Requires-Dist: sotabenchapi (>=0.0.13)
Requires-Dist: torch (>=1.1.0)
Requires-Dist: torchvision (>=0.3.0)
Requires-Dist: tqdm (>=4.32.2)
